proxytest/__init__.py
proxytest/__main__.py
proxytest/backend.py
proxytest/context.py
proxytest/parallel.py
proxytest/proxytest.py
proxytest/urls.py
proxytest/version.py
proxytest/backends/dummy.py
proxytest/backends/requests.py
proxytest/backends/simple.py
proxytest/backends/aiohttp/__init__.py
proxytest/backends/aiohttp/_aiohttp_python35.py
proxytest-0.5.4.dist-info/LICENSE.txt
proxytest-0.5.4.dist-info/METADATA
proxytest-0.5.4.dist-info/WHEEL
proxytest-0.5.4.dist-info/entry_points.txt
proxytest-0.5.4.dist-info/top_level.txt
proxytest-0.5.4.dist-info/RECORD
