Metadata-Version: 2.1
Name: proxytest
Version: 0.5.4
Summary: A simple script to test if one or more HTTP proxies are working by fetching a webpage.
Home-page: https://github.com/yoleg/proxytest
Author: Oleg Pryadko
Author-email: oleg@olegpryadko.com
Maintainer: Oleg Pryadko
Maintainer-email: oleg@olegpryadko.com
License: MIT
Keywords: proxy test command multiple proxies
Platform: UNKNOWN
Classifier: Environment :: Console
Classifier: Programming Language :: Python :: 3.4
Classifier: Programming Language :: Python :: 3.5
Classifier: Programming Language :: Python :: 3.6
Classifier: Programming Language :: Python :: 3.7
Requires-Dist: typing (<4.0,>=3.6.0) ; python_version < "3.5.0"
Provides-Extra: aiohttp
Requires-Dist: aiohttp ; extra == 'aiohttp'
Provides-Extra: all
Requires-Dist: aiohttp ; extra == 'all'
Requires-Dist: requests ; extra == 'all'
Provides-Extra: requests
Requires-Dist: requests ; extra == 'requests'
